bd_geocode_offline/__init__.py
bd_geocode_offline/core.py
bd_geocode_offline/utils.py
bd_geocode_offline/data/__init__.py
bd_geocode_offline/data/country_index.pkl.gz
bd_geocode_offline/data/geonames_data.jsonl.gz
bd_geocode_offline/data/metadata.json
bd_geocode_offline/data/postal_index.pkl.gz
bd_geocode_offline/data/sample_data.jsonl.gz
bd_geocode_offline-1.0.0.dist-info/licenses/LICENSE
examples/__init__.py
examples/advanced_usage.py
examples/basic_usage.py
examples/cli_example.py
scripts/__init__.py
scripts/build_package.py
scripts/download_data.py
tests/__init__.py
tests/test_core.py
tests/test_data.py
tests/test_performance.py
bd_geocode_offline-1.0.0.dist-info/METADATA
bd_geocode_offline-1.0.0.dist-info/WHEEL
bd_geocode_offline-1.0.0.dist-info/top_level.txt
bd_geocode_offline-1.0.0.dist-info/RECORD
