Metadata-Version: 2.4
Name: bd-geocode-offline
Version: 1.0.0
Summary: Complete offline GeoNames postal code database
Author: Karthikeyan Balasundaram
Classifier: Programming Language :: Python :: 3
Classifier: License :: OSI Approved :: MIT License
Classifier: Operating System :: OS Independent
Requires-Python: >=3.7
License-File: LICENSE
Dynamic: license-file
